poetry_template/__init__.py
poetry_template/package_one/__init__.py
poetry_template/package_one/module_one.py
poetry_template/package_two/__init__.py
poetry_template/package_two/module_two.py
poetry_template/profiler.py
poetry_template/runner.py
poetry_template/settings.py
poetry_template-0.1.4.dist-info/entry_points.txt
poetry_template-0.1.4.dist-info/LICENSE
poetry_template-0.1.4.dist-info/WHEEL
poetry_template-0.1.4.dist-info/METADATA
poetry_template-0.1.4.dist-info/RECORD
