Metadata-Version: 2.1
Name: poetry-template
Version: 0.1.4
Summary: A minimal, strictly structured Python project template.
Home-page: https://github.com/MislavJaksic/Python-Project-Template
License: MIT
Author: Mislav Jaksic
Author-email: jaksicmislav@gmail.com
Requires-Python: >=3.8,<4.0
Classifier: License :: OSI Approved :: MIT License
Classifier: Programming Language :: Python :: 3
Classifier: Programming Language :: Python :: 3.10
Classifier: Programming Language :: Python :: 3.8
Classifier: Programming Language :: Python :: 3.9
Requires-Dist: loguru (>=0.6.0,<0.7.0)
Requires-Dist: requests (>=2.27.1,<3.0.0)
Project-URL: Documentation, https://github.com/MislavJaksic/Python-Project-Template
Project-URL: Repository, https://github.com/MislavJaksic/Python-Project-Template
